odoo9_addon_html_image_url_extractor-9.0.1.0.0-py2.7-nspkg.pth
odoo9_addon_html_image_url_extractor-9.0.1.0.0.dist-info/top_level.txt
odoo9_addon_html_image_url_extractor-9.0.1.0.0.dist-info/WHEEL
odoo9_addon_html_image_url_extractor-9.0.1.0.0.dist-info/RECORD
odoo9_addon_html_image_url_extractor-9.0.1.0.0.dist-info/metadata.json
odoo9_addon_html_image_url_extractor-9.0.1.0.0.dist-info/DESCRIPTION.rst
odoo9_addon_html_image_url_extractor-9.0.1.0.0.dist-info/METADATA
odoo9_addon_html_image_url_extractor-9.0.1.0.0.dist-info/namespace_packages.txt
odoo_addons/html_image_url_extractor/__openerp__.py
odoo_addons/html_image_url_extractor/__init__.py
odoo_addons/html_image_url_extractor/README.rst
odoo_addons/html_image_url_extractor/models/ir_fields_converter.py
odoo_addons/html_image_url_extractor/models/__init__.py
odoo_addons/html_image_url_extractor/tests/__init__.py
odoo_addons/html_image_url_extractor/tests/test_extractor.py
odoo_addons/html_image_url_extractor/static/description/icon.png
